photo_gps/DSCF0311.xmp
photo_gps/DSCF0312.xmp
photo_gps/DSCF0313.xmp
photo_gps/__init__.py
photo_gps/commands.py
photo_gps/config.py
photo_gps/gui.py
photo_gps/jinja/xmp.jinja
photo_gps/photogps.example.yaml
photo_gps/photogps.py
photo_gps/tools.py
photo_gps_client-0.1.17.dist-info/METADATA
photo_gps_client-0.1.17.dist-info/WHEEL
photo_gps_client-0.1.17.dist-info/entry_points.txt
photo_gps_client-0.1.17.dist-info/RECORD
